yowasp_runtime/__init__.py
yowasp_runtime-1.84.dist-info/licenses/LICENSE.txt
yowasp_runtime-1.84.dist-info/METADATA
yowasp_runtime-1.84.dist-info/WHEEL
yowasp_runtime-1.84.dist-info/top_level.txt
yowasp_runtime-1.84.dist-info/RECORD
