Metadata-Version: 2.4
Name: yowasp-runtime
Version: 1.84
Summary: Common runtime for YoWASP packages
Author-email: Catherine <whitequark@whitequark.org>
License-Expression: ISC
Project-URL: Homepage, https://yowasp.org/
Project-URL: Source Code, https://github.com/YoWASP/runtime-py
Project-URL: Bug Tracker, https://github.com/YoWASP/runtime-py/issues
Requires-Python: ~=3.8
License-File: LICENSE.txt
Requires-Dist: importlib_resources; python_version < "3.9"
Requires-Dist: platformdirs<5,>=3.0
Requires-Dist: wasmtime<42,>=21.0.0
Dynamic: license-file
